drace/__init__.py
drace/__main__.py
drace/cli.py
drace/config.py
drace/constants.py
drace/docs.py
drace/help_menu.py
drace/native_lang.py
drace/py.typed
drace/types.py
drace/utils.py
drace/darkian/__init__.py
drace/darkian/z1/__init__.py
drace/darkian/z1/z100.py
drace/darkian/z1/z101.py
drace/darkian/z2/__init__.py
drace/darkian/z2/z200.py
drace/darkian/z2/z201.py
drace/darkian/z2/z202.py
drace/darkian/z2/z227.py
drace/darkian/z2/z22_.py
drace/linter/__init__.py
drace/linter/engine.py
drace/linter/pycodestyle.py
drace/linter/pyflakes/__init__.py
drace/linter/pyflakes/checker.py
drace/linter/pyflakes/flake_api.py
drace/linter/pyflakes/messages.py
drace/linter/pyflakes/reporter.py
drace/linter/pyflakes/test/__init__.py
drace/linter/pyflakes/test/harness.py
drace/linter/pyflakes/test/test_api.py
drace/linter/pyflakes/test/test_builtin.py
drace/linter/pyflakes/test/test_code_segment.py
drace/linter/pyflakes/test/test_dict.py
drace/linter/pyflakes/test/test_doctests.py
drace/linter/pyflakes/test/test_imports.py
drace/linter/pyflakes/test/test_is_literal.py
drace/linter/pyflakes/test/test_match.py
drace/linter/pyflakes/test/test_other.py
drace/linter/pyflakes/test/test_type_annotations.py
drace/linter/pyflakes/test/test_undefined_names.py
drace/reporters/__init__.py
drace/reporters/formatting.py
drace/reporters/linting.py
drace-2.0.6.dist-info/licenses/LICENSE
drace-2.0.6.dist-info/METADATA
drace-2.0.6.dist-info/WHEEL
drace-2.0.6.dist-info/entry_points.txt
drace-2.0.6.dist-info/top_level.txt
drace-2.0.6.dist-info/RECORD
