Metadata-Version: 2.4
Name: drace
Version: 2.0.6
Summary: A pragmatic, resilient Python linter and formatter
Author: Caleb M. Sibanda
Author-email: darkian.dev@gmail.com
License: MIT
Project-URL: Homepage, https://github.com/2kDarki/drace
Project-URL: Documentation, https://github.com/2kDarki/drace#readme
Project-URL: Repository, https://github.com/2kDarki/drace
Project-URL: Issues, https://github.com/2kDarki/drace/issues
Keywords: linter,formatter,python,cli,ast,code-quality,pragmatic,resilient
Classifier: Development Status :: 5 - Production/Stable
Classifier: Environment :: Console
Classifier: Intended Audience :: Developers
Classifier: License :: OSI Approved :: MIT License
Classifier: Operating System :: OS Independent
Classifier: Programming Language :: Python :: 3
Classifier: Programming Language :: Python :: 3 :: Only
Classifier: Programming Language :: Python :: 3.10
Classifier: Programming Language :: Python :: 3.11
Classifier: Programming Language :: Python :: 3.12
Classifier: Topic :: Software Development :: Libraries :: Python Modules
Classifier: Topic :: Software Development :: Quality Assurance
Requires-Python: >=3.10
License-File: LICENSE
Requires-Dist: cnat
Requires-Dist: tuikit>=0.1.3
Dynamic: author
Dynamic: author-email
Dynamic: license-file
